README.md
setup.py
cache_map/__init__.py
cache_map/cache_map.py
cache_map.egg-info/PKG-INFO
cache_map.egg-info/SOURCES.txt
cache_map.egg-info/dependency_links.txt
cache_map.egg-info/not-zip-safe
cache_map.egg-info/top_level.txt