Metadata-Version: 2.1
Name: cache-map
Version: 0.4
Summary: Cache Mapping for Direct and LRU mapping.
Home-page: UNKNOWN
Author: Rahul Sunil
Author-email: rahulsunil2@gmail.com
License: UNKNOWN
Platform: UNKNOWN
